{"meta":{"Title":"MYTHS AND MEN [New York Times, Sunday, January 11, 1948]","Author":"Alberta N. Burton","Editor":"Margaret Farrar","Date":"1948-01-11"},"grid":[["M","U","S","C","O","V","Y","#","H","E","A","D","S","E","T","#","P","A","L","O","M","A","R"],["A","S","T","O","R","I","A","#","A","L","T","A","I","T","E","#","E","M","U","L","A","T","E"],["C","H","I","N","O","O","K","#","R","E","T","R","A","C","T","#","T","E","M","P","L","A","R"],["H","U","N","S","#","L","I","B","R","A","S","#","M","E","R","M","E","N","#","S","A","V","E"],["I","A","N","#","#","A","M","A","I","N","#","#","#","T","A","U","R","T","#","#","B","I","N"],["N","I","E","P","A","#","A","L","S","O","P","#","G","E","G","G","S","#","B","L","A","S","T"],["E","A","S","E","R","S","#","T","O","R","O","T","O","R","O","S","#","R","E","A","R","M","S"],["#","#","#","E","R","I","C","#","N","A","P","A","E","A","N","#","P","E","R","E","#","#","#"],["J","E","T","P","I","L","O","T","#","#","E","F","T","#","#","S","O","D","A","L","I","M","E"],["A","R","R","E","S","T","E","R","#","S","Y","T","H","E","#","P","L","A","T","I","N","U","M"],["M","O","O","R","#","S","T","I","F","L","E","#","E","S","S","O","I","N","#","A","G","R","A"],["E","S","T","#","#","#","E","G","B","A","#","#","#","T","A","U","T","#","#","#","R","I","N"],["S","I","T","E","#","A","R","G","I","V","E","#","T","H","I","S","B","E","#","D","A","N","A"],["O","V","E","R","L","I","N","E","#","S","A","M","O","S","#","E","U","L","E","R","I","A","N"],["N","E","R","V","U","L","A","R","#","#","T","A","O","#","#","D","R","A","G","O","N","E","T"],["#","#","#","I","C","E","L","#","H","E","E","L","T","A","P","#","O","N","G","O","#","#","#"],["M","A","E","N","A","D","#","F","O","R","R","E","S","T","A","L","#","D","E","P","U","T","E"],["O","R","L","E","S","#","C","O","S","E","S","#","Y","A","T","E","S","#","D","Y","N","E","S"],["N","E","E","#","#","K","R","U","P","P","#","#","#","L","E","T","H","E","#","#","H","A","P"],["I","N","G","A","#","A","U","R","I","T","E","#","P","A","N","O","A","N","#","L","I","S","A"],["T","O","I","L","E","R","S","#","T","A","R","R","A","N","T","#","S","T","A","I","N","E","D"],["O","S","S","E","L","E","T","#","A","S","T","A","R","T","E","#","T","A","N","A","G","R","A"],["R","E","T","A","I","L","S","#","L","E","S","T","R","A","D","#","A","D","D","R","E","S","S"]],"across":[{"num":"A1","question":"Old name of Russia.","answer":"MUSCOVY"},{"num":"A8","question":"Plane pilot's equipment.","answer":"HEADSET"},{"num":"A15","question":"Mt. ___, site of new giant telescope.","answer":"PALOMAR"},{"num":"A22","question":"Port in NW corner of Oregon.","answer":"ASTORIA"},{"num":"A23","question":"Lead telluride from Alta Mts.","answer":"ALTAITE"},{"num":"A24","question":"Rival.","answer":"EMULATE"},{"num":"A25","question":"Warm, dry wind from the Rockies.","answer":"CHINOOK"},{"num":"A26","question":"Withdraw.","answer":"RETRACT"},{"num":"A27","question":"12th century guardian of the Holy Sepulcher.","answer":"TEMPLAR"},{"num":"A28","question":"Boches.","answer":"HUNS"},{"num":"A29","question":"1.012 lbs. each in Brazil.","answer":"LIBRAS"},{"num":"A31","question":"Mermaids' boy friends.","answer":"MERMEN"},{"num":"A33","question":"Rescue.","answer":"SAVE"},{"num":"A34","question":"Gaelic John.","answer":"IAN"},{"num":"A35","question":"Forcefully.","answer":"AMAIN"},{"num":"A36","question":"Consort of Set.","answer":"TAURT"},{"num":"A37","question":"Crib.","answer":"BIN"},{"num":"A38","question":"Medicinal bitter bark of the Samandura tree.","answer":"NIEPA"},{"num":"A41","question":"Washington columnist.","answer":"ALSOP"},{"num":"A43","question":"Hoaxes: Scot.","answer":"GEGGS"},{"num":"A44","question":"Diatribe.","answer":"BLAST"},{"num":"A46","question":"Slackening bars in loom.","answer":"EASERS"},{"num":"A48","question":"Kingfishers of New Guinea: Native name.","answer":"TOROTOROS"},{"num":"A50","question":"Furnishes with new weapons.","answer":"REARMS"},{"num":"A51","question":"10th century discoverer and colonizer of Greenland.","answer":"ERIC"},{"num":"A53","question":"Pertaining to the wood nymphs: Gr. myth.","answer":"NAPAEAN"},{"num":"A54","question":"Father: Fr.","answer":"PERE"},{"num":"A55","question":"1947 Derby winner.","answer":"JETPILOT"},{"num":"A59","question":"Newt.","answer":"EFT"},{"num":"A60","question":"Absorbent mixture used in gas masks.","answer":"SODALIME"},{"num":"A64","question":"Detainer.","answer":"ARRESTER"},{"num":"A65","question":"Mowing instrument: Var.","answer":"SYTHE"},{"num":"A67","question":"Precious metal.","answer":"PLATINUM"},{"num":"A68","question":"Othello.","answer":"MOOR"},{"num":"A69","question":"Choke.","answer":"STIFLE"},{"num":"A71","question":"Excuse for nonappearance in court.","answer":"ESSOIN"},{"num":"A73","question":"Site of the Taj Mahal.","answer":"AGRA"},{"num":"A74","question":"Eastern standard time.","answer":"EST"},{"num":"A75","question":"Most powerful tribe of the Yoruba peoples.","answer":"EGBA"},{"num":"A76","question":"Tense.","answer":"TAUT"},{"num":"A77","question":"Japanese measure.","answer":"RIN"},{"num":"A78","question":"Location.","answer":"SITE"},{"num":"A80","question":"A Greek of Argos.","answer":"ARGIVE"},{"num":"A82","question":"Sweetheart of Pyramus.","answer":"THISBE"},{"num":"A84","question":"Charles A. ___, famous editor (1819–97).","answer":"DANA"},{"num":"A85","question":"Accentuate.","answer":"OVERLINE"},{"num":"A87","question":"Birthplace of Pythagoras.","answer":"SAMOS"},{"num":"A89","question":"Of the equations of a famous Swiss mathematician.","answer":"EULERIAN"},{"num":"A91","question":"Relating to small nerves.","answer":"NERVULAR"},{"num":"A92","question":"Cosmic order: Chinese Philos.","answer":"TAO"},{"num":"A93","question":"Little dragon.","answer":"DRAGONET"},{"num":"A94","question":"Land of geysers: Abbr.","answer":"ICEL"},{"num":"A95","question":"Part of a shoe.","answer":"HEELTAP"},{"num":"A99","question":"Act of going forward.","answer":"ONGO"},{"num":"A100","question":"Bacchante.","answer":"MAENAD"},{"num":"A103","question":"Secretary of Defense.","answer":"FORRESTAL"},{"num":"A105","question":"Delegate.","answer":"DEPUTE"},{"num":"A109","question":"Chaplets: Her.","answer":"ORLES"},{"num":"A110","question":"Friendly chats: Var.","answer":"COSES"},{"num":"A111","question":"Richard ___, Civil War Governor of Illinois.","answer":"YATES"},{"num":"A113","question":"Units of force.","answer":"DYNES"},{"num":"A114","question":"Born.","answer":"NEE"},{"num":"A115","question":"Head of German armament works.","answer":"KRUPP"},{"num":"A116","question":"River of Hades.","answer":"LETHE"},{"num":"A118","question":"Chance.","answer":"HAP"},{"num":"A119","question":"Guama, shade tree for coffee plantations.","answer":"INGA"},{"num":"A121","question":"Salt of aurous acid.","answer":"AURITE"},{"num":"A123","question":"Designating Indians of Brazil, Peru and Bolivia.","answer":"PANOAN"},{"num":"A124","question":"Diminutive of Elizabeth.","answer":"LISA"},{"num":"A125","question":"Slaves.","answer":"TOILERS"},{"num":"A127","question":"Ft. Worth is county seat of this county.","answer":"TARRANT"},{"num":"A129","question":"Discolored.","answer":"STAINED"},{"num":"A131","question":"Little bone.","answer":"OSSELET"},{"num":"A132","question":"Phoenician goddess of love.","answer":"ASTARTE"},{"num":"A133","question":"Greek terra cotta figurine.","answer":"TANAGRA"},{"num":"A134","question":"Gossips.","answer":"RETAILS"},{"num":"A135","question":"2.84 bushels in Wales.","answer":"LESTRAD"},{"num":"A136","question":"Speech.","answer":"ADDRESS"}],"down":[{"num":"D1","question":"Political organization.","answer":"MACHINE"},{"num":"D2","question":"World's southernmost city, capital of Tierra del Fuego.","answer":"USHUAIA"},{"num":"D3","question":"Ruhr steel magnate and banker (1870–1924).","answer":"STINNES"},{"num":"D4","question":"Studies.","answer":"CONS"},{"num":"D5","question":"Polynesian god of war.","answer":"ORO"},{"num":"D6","question":"Duke Orsino's page in \"Twelfth Night.\"","answer":"VIOLA"},{"num":"D7","question":"City and river in Washington.","answer":"YAKIMA"},{"num":"D8","question":"Chief architect of United Nations city.","answer":"HARRISON"},{"num":"D9","question":"___ Duse.","answer":"ELEANORA"},{"num":"D10","question":"Pewter coins of Siam.","answer":"ATTS"},{"num":"D11","question":"Patriotic society.","answer":"DAR"},{"num":"D12","question":"Land of the sacred white elephant.","answer":"SIAM"},{"num":"D13","question":"And so on.","answer":"ETCETERA"},{"num":"D14","question":"Quadrangle.","answer":"TETRAGON"},{"num":"D15","question":"Comes to nothing.","answer":"PETERS"},{"num":"D16","question":"Catkin.","answer":"AMENT"},{"num":"D17","question":"Abner's sidekick.","answer":"LUM"},{"num":"D18","question":"Bullfinches: Var.","answer":"OLPS"},{"num":"D19","question":"Calicut is its capital.","answer":"MALABAR"},{"num":"D20","question":"Reversion to primitive type.","answer":"ATAVISM"},{"num":"D21","question":"Sublets.","answer":"RERENTS"},{"num":"D30","question":"A Lithuanian.","answer":"BALT"},{"num":"D32","question":"Steins.","answer":"MUGS"},{"num":"D39","question":"Small tree frog.","answer":"PEEPER"},{"num":"D40","question":"Raised edge between flutings in Doric column.","answer":"ARRIS"},{"num":"D42","question":"The Sailor Man.","answer":"POPEYE"},{"num":"D43","question":"Author of \"Faust.\"","answer":"GOETHE"},{"num":"D44","question":"Oriental sovereign's grant of privilege.","answer":"BERAT"},{"num":"D45","question":"Large genus of beautiful orchids.","answer":"LAELIA"},{"num":"D47","question":"Becomes choked with sediment.","answer":"SILTS"},{"num":"D49","question":"Co-author of labor act.","answer":"TAFT"},{"num":"D50","question":"Fortification.","answer":"REDAN"},{"num":"D52","question":"Equally everlasting.","answer":"COETERNAL"},{"num":"D54","question":"Russia's governing body.","answer":"POLITBURO"},{"num":"D55","question":"Cecil Rhodes' right-hand man.","answer":"JAMESON"},{"num":"D56","question":"Wearing away.","answer":"EROSIVE"},{"num":"D57","question":"Sulky racer.","answer":"TROTTER"},{"num":"D58","question":"Roy Rogers' co-star.","answer":"TRIGGER"},{"num":"D60","question":"Wedded: Archaic.","answer":"SPOUSED"},{"num":"D61","question":"Saturate.","answer":"INGRAIN"},{"num":"D62","question":"Rats and mice: Zool.","answer":"MURINAE"},{"num":"D63","question":"Issuing.","answer":"EMANANT"},{"num":"D65","question":"Balkan peoples.","answer":"SLAVS"},{"num":"D66","question":"Natives of Estonia.","answer":"ESTHS"},{"num":"D70","question":"Hoover's bureau.","answer":"FBI"},{"num":"D72","question":"Capuchin monkey.","answer":"SAI"},{"num":"D79","question":"St. John ___, Irish dramatist, author of \"John Ferguson.\"","answer":"ERVINE"},{"num":"D80","question":"Troubled.","answer":"AILED"},{"num":"D81","question":"Gourmands.","answer":"EATERS"},{"num":"D82","question":"Foot: Childish word.","answer":"TOOTSY"},{"num":"D83","question":"African antelope.","answer":"ELAND"},{"num":"D84","question":"Limp.","answer":"DROOPY"},{"num":"D86","question":"Senator from Illinois.","answer":"LUCAS"},{"num":"D88","question":"Masculine.","answer":"MALE"},{"num":"D90","question":"Incited.","answer":"EGGED"},{"num":"D95","question":"Sick bay.","answer":"HOSPITAL"},{"num":"D96","question":"Digestive enzyme.","answer":"EREPTASE"},{"num":"D97","question":"Golden apples cost her a race.","answer":"ATALANTA"},{"num":"D98","question":"Protected, as an invention, by Government letters.","answer":"PATENTED"},{"num":"D100","question":"She met and checked the Merrimac.","answer":"MONITOR"},{"num":"D101","question":"Sandy.","answer":"ARENOSE"},{"num":"D102","question":"Writer of laments.","answer":"ELEGIST"},{"num":"D103","question":"Number of the apocalyptic horsemen.","answer":"FOUR"},{"num":"D104","question":"Mother of Apollo.","answer":"LETO"},{"num":"D106","question":"Dislocate.","answer":"UNHINGE"},{"num":"D107","question":"Plaguers.","answer":"TEASERS"},{"num":"D108","question":"Matadors: Sp.","answer":"ESPADAS"},{"num":"D110","question":"Dry bread.","answer":"CRUSTS"},{"num":"D112","question":"High volcanic peak in N. California.","answer":"SHASTA"},{"num":"D115","question":"Finnish dialect.","answer":"KAREL"},{"num":"D117","question":"Inwards: Anat.","answer":"ENTAD"},{"num":"D120","question":"Athena ___, Greek goddess of light.","answer":"ALEA"},{"num":"D122","question":"Urges on: Scot.","answer":"ERTS"},{"num":"D123","question":"Catherine ___, sixth wife of Henry VIII.","answer":"PARR"},{"num":"D124","question":"Bible synonym for Satan.","answer":"LIAR"},{"num":"D126","question":"___ Yale.","answer":"ELI"},{"num":"D128","question":"Rodent.","answer":"RAT"},{"num":"D130","question":"Conjunction.","answer":"AND"}],"rawGrid":"\nMUSCOVY#HEADSET#PALOMAR\nASTORIA#ALTAITE#EMULATE\nCHINOOK#RETRACT#TEMPLAR\nHUNS#LIBRAS#MERMEN#SAVE\nIAN##AMAIN###TAURT##BIN\nNIEPA#ALSOP#GEGGS#BLAST\nEASERS#TOROTOROS#REARMS\n###ERIC#NAPAEAN#PERE###\nJETPILOT##EFT##SODALIME\nARRESTER#SYTHE#PLATINUM\nMOOR#STIFLE#ESSOIN#AGRA\nEST###EGBA###TAUT###RIN\nSITE#ARGIVE#THISBE#DANA\nOVERLINE#SAMOS#EULERIAN\nNERVULAR##TAO##DRAGONET\n###ICEL#HEELTAP#ONGO###\nMAENAD#FORRESTAL#DEPUTE\nORLES#COSES#YATES#DYNES\nNEE##KRUPP###LETHE##HAP\nINGA#AURITE#PANOAN#LISA\nTOILERS#TARRANT#STAINED\nOSSELET#ASTARTE#TANAGRA\nRETAILS#LESTRAD#ADDRESS\n","rawAcross":"\nA1. Old name of Russia. ~ MUSCOVY\nA8. Plane pilot's equipment. ~ HEADSET\nA15. Mt. ___, site of new giant telescope. ~ PALOMAR\nA22. Port in NW corner of Oregon. ~ ASTORIA\nA23. Lead telluride from Alta Mts. ~ ALTAITE\nA24. Rival. ~ EMULATE\nA25. Warm, dry wind from the Rockies. ~ CHINOOK\nA26. Withdraw. ~ RETRACT\nA27. 12th century guardian of the Holy Sepulcher. ~ TEMPLAR\nA28. Boches. ~ HUNS\nA29. 1.012 lbs. each in Brazil. ~ LIBRAS\nA31. Mermaids' boy friends. ~ MERMEN\nA33. Rescue. ~ SAVE\nA34. Gaelic John. ~ IAN\nA35. Forcefully. ~ AMAIN\nA36. Consort of Set. ~ TAURT\nA37. Crib. ~ BIN\nA38. Medicinal bitter bark of the Samandura tree. ~ NIEPA\nA41. Washington columnist. ~ ALSOP\nA43. Hoaxes: Scot. ~ GEGGS\nA44. Diatribe. ~ BLAST\nA46. Slackening bars in loom. ~ EASERS\nA48. Kingfishers of New Guinea: Native name. ~ TOROTOROS\nA50. Furnishes with new weapons. ~ REARMS\nA51. 10th century discoverer and colonizer of Greenland. ~ ERIC\nA53. Pertaining to the wood nymphs: Gr. myth. ~ NAPAEAN\nA54. Father: Fr. ~ PERE\nA55. 1947 Derby winner. ~ JETPILOT\nA59. Newt. ~ EFT\nA60. Absorbent mixture used in gas masks. ~ SODALIME\nA64. Detainer. ~ ARRESTER\nA65. Mowing instrument: Var. ~ SYTHE\nA67. Precious metal. ~ PLATINUM\nA68. Othello. ~ MOOR\nA69. Choke. ~ STIFLE\nA71. Excuse for nonappearance in court. ~ ESSOIN\nA73. Site of the Taj Mahal. ~ AGRA\nA74. Eastern standard time. ~ EST\nA75. Most powerful tribe of the Yoruba peoples. ~ EGBA\nA76. Tense. ~ TAUT\nA77. Japanese measure. ~ RIN\nA78. Location. ~ SITE\nA80. A Greek of Argos. ~ ARGIVE\nA82. Sweetheart of Pyramus. ~ THISBE\nA84. Charles A. ___, famous editor (1819–97). ~ DANA\nA85. Accentuate. ~ OVERLINE\nA87. Birthplace of Pythagoras. ~ SAMOS\nA89. Of the equations of a famous Swiss mathematician. ~ EULERIAN\nA91. Relating to small nerves. ~ NERVULAR\nA92. Cosmic order: Chinese Philos. ~ TAO\nA93. Little dragon. ~ DRAGONET\nA94. Land of geysers: Abbr. ~ ICEL\nA95. Part of a shoe. ~ HEELTAP\nA99. Act of going forward. ~ ONGO\nA100. Bacchante. ~ MAENAD\nA103. Secretary of Defense. ~ FORRESTAL\nA105. Delegate. ~ DEPUTE\nA109. Chaplets: Her. ~ ORLES\nA110. Friendly chats: Var. ~ COSES\nA111. Richard ___, Civil War Governor of Illinois. ~ YATES\nA113. Units of force. ~ DYNES\nA114. Born. ~ NEE\nA115. Head of German armament works. ~ KRUPP\nA116. River of Hades. ~ LETHE\nA118. Chance. ~ HAP\nA119. Guama, shade tree for coffee plantations. ~ INGA\nA121. Salt of aurous acid. ~ AURITE\nA123. Designating Indians of Brazil, Peru and Bolivia. ~ PANOAN\nA124. Diminutive of Elizabeth. ~ LISA\nA125. Slaves. ~ TOILERS\nA127. Ft. Worth is county seat of this county. ~ TARRANT\nA129. Discolored. ~ STAINED\nA131. Little bone. ~ OSSELET\nA132. Phoenician goddess of love. ~ ASTARTE\nA133. Greek terra cotta figurine. ~ TANAGRA\nA134. Gossips. ~ RETAILS\nA135. 2.84 bushels in Wales. ~ LESTRAD\nA136. Speech. ~ ADDRESS\n","rawDown":"\nD1. Political organization. ~ MACHINE\nD2. World's southernmost city, capital of Tierra del Fuego. ~ USHUAIA\nD3. Ruhr steel magnate and banker (1870–1924). ~ STINNES\nD4. Studies. ~ CONS\nD5. Polynesian god of war. ~ ORO\nD6. Duke Orsino's page in \"Twelfth Night.\" ~ VIOLA\nD7. City and river in Washington. ~ YAKIMA\nD8. Chief architect of United Nations city. ~ HARRISON\nD9. ___ Duse. ~ ELEANORA\nD10. Pewter coins of Siam. ~ ATTS\nD11. Patriotic society. ~ DAR\nD12. Land of the sacred white elephant. ~ SIAM\nD13. And so on. ~ ETCETERA\nD14. Quadrangle. ~ TETRAGON\nD15. Comes to nothing. ~ PETERS\nD16. Catkin. ~ AMENT\nD17. Abner's sidekick. ~ LUM\nD18. Bullfinches: Var. ~ OLPS\nD19. Calicut is its capital. ~ MALABAR\nD20. Reversion to primitive type. ~ ATAVISM\nD21. Sublets. ~ RERENTS\nD30. A Lithuanian. ~ BALT\nD32. Steins. ~ MUGS\nD39. Small tree frog. ~ PEEPER\nD40. Raised edge between flutings in Doric column. ~ ARRIS\nD42. The Sailor Man. ~ POPEYE\nD43. Author of \"Faust.\" ~ GOETHE\nD44. Oriental sovereign's grant of privilege. ~ BERAT\nD45. Large genus of beautiful orchids. ~ LAELIA\nD47. Becomes choked with sediment. ~ SILTS\nD49. Co-author of labor act. ~ TAFT\nD50. Fortification. ~ REDAN\nD52. Equally everlasting. ~ COETERNAL\nD54. Russia's governing body. ~ POLITBURO\nD55. Cecil Rhodes' right-hand man. ~ JAMESON\nD56. Wearing away. ~ EROSIVE\nD57. Sulky racer. ~ TROTTER\nD58. Roy Rogers' co-star. ~ TRIGGER\nD60. Wedded: Archaic. ~ SPOUSED\nD61. Saturate. ~ INGRAIN\nD62. Rats and mice: Zool. ~ MURINAE\nD63. Issuing. ~ EMANANT\nD65. Balkan peoples. ~ SLAVS\nD66. Natives of Estonia. ~ ESTHS\nD70. Hoover's bureau. ~ FBI\nD72. Capuchin monkey. ~ SAI\nD79. St. John ___, Irish dramatist, author of \"John Ferguson.\" ~ ERVINE\nD80. Troubled. ~ AILED\nD81. Gourmands. ~ EATERS\nD82. Foot: Childish word. ~ TOOTSY\nD83. African antelope. ~ ELAND\nD84. Limp. ~ DROOPY\nD86. Senator from Illinois. ~ LUCAS\nD88. Masculine. ~ MALE\nD90. Incited. ~ EGGED\nD95. Sick bay. ~ HOSPITAL\nD96. Digestive enzyme. ~ EREPTASE\nD97. Golden apples cost her a race. ~ ATALANTA\nD98. Protected, as an invention, by Government letters. ~ PATENTED\nD100. She met and checked the Merrimac. ~ MONITOR\nD101. Sandy. ~ ARENOSE\nD102. Writer of laments. ~ ELEGIST\nD103. Number of the apocalyptic horsemen. ~ FOUR\nD104. Mother of Apollo. ~ LETO\nD106. Dislocate. ~ UNHINGE\nD107. Plaguers. ~ TEASERS\nD108. Matadors: Sp. ~ ESPADAS\nD110. Dry bread. ~ CRUSTS\nD112. High volcanic peak in N. California. ~ SHASTA\nD115. Finnish dialect. ~ KAREL\nD117. Inwards: Anat. ~ ENTAD\nD120. Athena ___, Greek goddess of light. ~ ALEA\nD122. Urges on: Scot. ~ ERTS\nD123. Catherine ___, sixth wife of Henry VIII. ~ PARR\nD124. Bible synonym for Satan. ~ LIAR\nD126. ___ Yale. ~ ELI\nD128. Rodent. ~ RAT\nD130. Conjunction. ~ AND\n","rawMeta":"Title: MYTHS AND MEN [New York Times, Sunday, January 11, 1948]\nAuthor: Alberta N. Burton\nEditor: Margaret Farrar\nDate: 1948-01-11\n"}