{"meta":{"Title":"New York Times, Thursday, July 29, 1965","Author":"Unknown","Editor":"Margaret Farrar","Date":"1965-07-29"},"grid":[["T","U","T","U","#","S","T","A","N","D","#","A","N","D","S"],["A","R","U","M","#","W","A","X","E","R","#","R","O","O","K"],["P","E","R","P","L","E","X","I","T","Y","#","O","N","L","Y"],["S","Y","N","#","I","D","E","S","#","D","I","M","P","L","E"],["#","#","#","B","E","E","S","#","C","O","R","A","L","#","#"],["I","M","P","U","G","N","#","C","O","C","K","S","U","R","E"],["N","O","U","S","E","#","W","O","R","K","S","#","S","A","M"],["C","O","Z","Y","#","B","A","N","K","S","#","R","S","V","P"],["A","D","Z","#","W","I","N","G","S","#","S","H","E","E","T"],["S","Y","L","L","A","B","L","E","#","T","H","U","S","L","Y"],["#","#","E","A","R","L","Y","#","C","U","R","S","#","#","#"],["G","E","M","I","N","I","#","S","A","N","E","#","T","O","A"],["A","V","E","R","#","C","O","N","U","N","D","R","U","M","S"],["L","E","N","D","#","A","B","U","S","E","#","U","N","I","T"],["A","R","T","S","#","L","I","B","E","L","#","G","A","T","O"]],"across":[{"num":"A1","question":"Dancer's skirt.","answer":"TUTU"},{"num":"A5","question":"Business site.","answer":"STAND"},{"num":"A10","question":"Conjunctions.","answer":"ANDS"},{"num":"A14","question":"Jack-in-the-pulpit.","answer":"ARUM"},{"num":"A15","question":"Housekeeping aid.","answer":"WAXER"},{"num":"A16","question":"Chessman.","answer":"ROOK"},{"num":"A17","question":"Complication.","answer":"PERPLEXITY"},{"num":"A19","question":"Pre-eminent.","answer":"ONLY"},{"num":"A20","question":"With: Prefix.","answer":"SYN"},{"num":"A21","question":"Roman date.","answer":"IDES"},{"num":"A22","question":"Indentation.","answer":"DIMPLE"},{"num":"A24","question":"Get-togethers, country style.","answer":"BEES"},{"num":"A25","question":"Marine skeletons.","answer":"CORAL"},{"num":"A26","question":"Challenge as false.","answer":"IMPUGN"},{"num":"A29","question":"Self-confident to an offensive degree.","answer":"COCKSURE"},{"num":"A32","question":"Have ___ for.","answer":"NOUSE"},{"num":"A33","question":"Opera.","answer":"WORKS"},{"num":"A34","question":"___ Rayburn, Polaris craft.","answer":"SAM"},{"num":"A35","question":"Comfortable.","answer":"COZY"},{"num":"A36","question":"Deposits.","answer":"BANKS"},{"num":"A37","question":"Request on invitations.","answer":"RSVP"},{"num":"A38","question":"Cutting tool.","answer":"ADZ"},{"num":"A39","question":"Aircraft units.","answer":"WINGS"},{"num":"A40","question":"Sail: Poet.","answer":"SHEET"},{"num":"A41","question":"Part of a word.","answer":"SYLLABLE"},{"num":"A43","question":"In this manner.","answer":"THUSLY"},{"num":"A44","question":"Betimes.","answer":"EARLY"},{"num":"A45","question":"Some canines.","answer":"CURS"},{"num":"A46","question":"U.S. space project.","answer":"GEMINI"},{"num":"A48","question":"Partner of safe.","answer":"SANE"},{"num":"A49","question":"___ turn (perfectly).","answer":"TOA"},{"num":"A52","question":"Affirm.","answer":"AVER"},{"num":"A53","question":"Puzzles.","answer":"CONUNDRUMS"},{"num":"A56","question":"Afford.","answer":"LEND"},{"num":"A57","question":"Mistreat.","answer":"ABUSE"},{"num":"A58","question":"One.","answer":"UNIT"},{"num":"A59","question":"Branches of learning.","answer":"ARTS"},{"num":"A60","question":"Traduce.","answer":"LIBEL"},{"num":"A61","question":"Cat: Sp.","answer":"GATO"}],"down":[{"num":"D1","question":"Lights out.","answer":"TAPS"},{"num":"D2","question":"Nobel physicist.","answer":"UREY"},{"num":"D3","question":"Variety act.","answer":"TURN"},{"num":"D4","question":"Man in blue.","answer":"UMP"},{"num":"D5","question":"Land of the Riksdag.","answer":"SWEDEN"},{"num":"D6","question":"One of life's certainties.","answer":"TAXES"},{"num":"D7","question":"Certain line.","answer":"AXIS"},{"num":"D8","question":"After expenses.","answer":"NET"},{"num":"D9","question":"Ship repair facilities.","answer":"DRYDOCKS"},{"num":"D10","question":"Bouquets.","answer":"AROMAS"},{"num":"D11","question":"Baffles.","answer":"NONPLUSSES"},{"num":"D12","question":"Paper ___.","answer":"DOLL"},{"num":"D13","question":"Terrier.","answer":"SKYE"},{"num":"D18","question":"City in Belgium.","answer":"LIEGE"},{"num":"D23","question":"Annoys.","answer":"IRKS"},{"num":"D24","question":"Engaged.","answer":"BUSY"},{"num":"D25","question":"Stoppers.","answer":"CORKS"},{"num":"D26","question":"People of Peru.","answer":"INCAS"},{"num":"D27","question":"Temperamental.","answer":"MOODY"},{"num":"D28","question":"See 17 Across.","answer":"PUZZLEMENT"},{"num":"D29","question":"Permission to leave.","answer":"CONGE"},{"num":"D30","question":"French composer.","answer":"RAVEL"},{"num":"D31","question":"Blank.","answer":"EMPTY"},{"num":"D33","question":"Pallidly.","answer":"WANLY"},{"num":"D36","question":"Of a sacred book.","answer":"BIBLICAL"},{"num":"D37","question":"Poison oak or ivy.","answer":"RHUS"},{"num":"D39","question":"Admonish.","answer":"WARN"},{"num":"D40","question":"Fragment.","answer":"SHRED"},{"num":"D42","question":"Men of the Highlands.","answer":"LAIRDS"},{"num":"D43","question":"Engineering feat.","answer":"TUNNEL"},{"num":"D45","question":"Antecedent.","answer":"CAUSE"},{"num":"D46","question":"Festive.","answer":"GALA"},{"num":"D47","question":"Unending.","answer":"EVER"},{"num":"D48","question":"Rebuff.","answer":"SNUB"},{"num":"D49","question":"Bluefin.","answer":"TUNA"},{"num":"D50","question":"Neglect.","answer":"OMIT"},{"num":"D51","question":"Concerning.","answer":"ASTO"},{"num":"D54","question":"Oriental sash.","answer":"OBI"},{"num":"D55","question":"Oriental.","answer":"RUG"}],"rawGrid":"\nTUTU#STAND#ANDS\nARUM#WAXER#ROOK\nPERPLEXITY#ONLY\nSYN#IDES#DIMPLE\n###BEES#CORAL##\nIMPUGN#COCKSURE\nNOUSE#WORKS#SAM\nCOZY#BANKS#RSVP\nADZ#WINGS#SHEET\nSYLLABLE#THUSLY\n##EARLY#CURS###\nGEMINI#SANE#TOA\nAVER#CONUNDRUMS\nLEND#ABUSE#UNIT\nARTS#LIBEL#GATO\n","rawAcross":"\nA1. Dancer's skirt. ~ TUTU\nA5. Business site. ~ STAND\nA10. Conjunctions. ~ ANDS\nA14. Jack-in-the-pulpit. ~ ARUM\nA15. Housekeeping aid. ~ WAXER\nA16. Chessman. ~ ROOK\nA17. Complication. ~ PERPLEXITY\nA19. Pre-eminent. ~ ONLY\nA20. With: Prefix. ~ SYN\nA21. Roman date. ~ IDES\nA22. Indentation. ~ DIMPLE\nA24. Get-togethers, country style. ~ BEES\nA25. Marine skeletons. ~ CORAL\nA26. Challenge as false. ~ IMPUGN\nA29. Self-confident to an offensive degree. ~ COCKSURE\nA32. Have ___ for. ~ NOUSE\nA33. Opera. ~ WORKS\nA34. ___ Rayburn, Polaris craft. ~ SAM\nA35. Comfortable. ~ COZY\nA36. Deposits. ~ BANKS\nA37. Request on invitations. ~ RSVP\nA38. Cutting tool. ~ ADZ\nA39. Aircraft units. ~ WINGS\nA40. Sail: Poet. ~ SHEET\nA41. Part of a word. ~ SYLLABLE\nA43. In this manner. ~ THUSLY\nA44. Betimes. ~ EARLY\nA45. Some canines. ~ CURS\nA46. U.S. space project. ~ GEMINI\nA48. Partner of safe. ~ SANE\nA49. ___ turn (perfectly). ~ TOA\nA52. Affirm. ~ AVER\nA53. Puzzles. ~ CONUNDRUMS\nA56. Afford. ~ LEND\nA57. Mistreat. ~ ABUSE\nA58. One. ~ UNIT\nA59. Branches of learning. ~ ARTS\nA60. Traduce. ~ LIBEL\nA61. Cat: Sp. ~ GATO\n","rawDown":"\nD1. Lights out. ~ TAPS\nD2. Nobel physicist. ~ UREY\nD3. Variety act. ~ TURN\nD4. Man in blue. ~ UMP\nD5. Land of the Riksdag. ~ SWEDEN\nD6. One of life's certainties. ~ TAXES\nD7. Certain line. ~ AXIS\nD8. After expenses. ~ NET\nD9. Ship repair facilities. ~ DRYDOCKS\nD10. Bouquets. ~ AROMAS\nD11. Baffles. ~ NONPLUSSES\nD12. Paper ___. ~ DOLL\nD13. Terrier. ~ SKYE\nD18. City in Belgium. ~ LIEGE\nD23. Annoys. ~ IRKS\nD24. Engaged. ~ BUSY\nD25. Stoppers. ~ CORKS\nD26. People of Peru. ~ INCAS\nD27. Temperamental. ~ MOODY\nD28. See 17 Across. ~ PUZZLEMENT\nD29. Permission to leave. ~ CONGE\nD30. French composer. ~ RAVEL\nD31. Blank. ~ EMPTY\nD33. Pallidly. ~ WANLY\nD36. Of a sacred book. ~ BIBLICAL\nD37. Poison oak or ivy. ~ RHUS\nD39. Admonish. ~ WARN\nD40. Fragment. ~ SHRED\nD42. Men of the Highlands. ~ LAIRDS\nD43. Engineering feat. ~ TUNNEL\nD45. Antecedent. ~ CAUSE\nD46. Festive. ~ GALA\nD47. Unending. ~ EVER\nD48. Rebuff. ~ SNUB\nD49. Bluefin. ~ TUNA\nD50. Neglect. ~ OMIT\nD51. Concerning. ~ ASTO\nD54. Oriental sash. ~ OBI\nD55. Oriental. ~ RUG\n","rawMeta":"Title: New York Times, Thursday, July 29, 1965\nAuthor: Unknown\nEditor: Margaret Farrar\nDate: 1965-07-29\n"}