{"meta":{"Title":"New York Times, Wednesday, October 14, 1959","Author":"Unknown","Editor":"Margaret Farrar","Date":"1959-10-14"},"grid":[["C","R","E","T","A","N","#","#","#","S","C","A","U","P","S"],["A","I","L","E","R","O","N","S","#","C","A","S","T","R","O"],["S","P","A","R","K","M","A","N","#","O","S","S","I","A","N"],["A","P","T","#","S","A","V","A","N","T","S","#","L","I","N"],["B","L","E","W","#","D","A","R","N","S","#","R","I","S","E"],["A","E","R","I","E","#","H","E","W","#","B","I","Z","E","T"],["#","#","#","S","A","G","O","S","#","M","I","T","E","R","S"],["#","C","O","P","S","E","#","#","#","F","O","U","R","S","#"],["S","O","V","I","E","T","#","C","A","R","T","A","#","#","#"],["O","G","E","E","S","#","F","O","P","#","A","L","G","E","R"],["B","I","R","R","#","B","O","B","U","P","#","S","O","S","O"],["E","T","A","#","P","E","B","B","L","E","D","#","U","S","A"],["R","A","G","O","U","T","#","L","I","N","E","A","G","E","S"],["E","T","E","R","N","E","#","E","A","S","E","M","E","N","T"],["R","E","S","E","A","L","#","#","#","E","R","A","S","E","S"]],"across":[{"num":"A1","question":"Native of Gnossus.","answer":"CRETAN"},{"num":"A7","question":"Sea ducks.","answer":"SCAUPS"},{"num":"A13","question":"Airplane parts.","answer":"AILERONS"},{"num":"A16","question":"Cuban notable.","answer":"CASTRO"},{"num":"A17","question":"Kefauver's running mate.","answer":"SPARKMAN"},{"num":"A18","question":"Bard of Irish folklore.","answer":"OSSIAN"},{"num":"A19","question":"Fitting.","answer":"APT"},{"num":"A20","question":"Learned men.","answer":"SAVANTS"},{"num":"A22","question":"Linden tree.","answer":"LIN"},{"num":"A23","question":"Was stormy.","answer":"BLEW"},{"num":"A25","question":"Mends.","answer":"DARNS"},{"num":"A26","question":"Begin.","answer":"RISE"},{"num":"A27","question":"Lofty abode.","answer":"AERIE"},{"num":"A29","question":"Chop.","answer":"HEW"},{"num":"A30","question":"French composer.","answer":"BIZET"},{"num":"A31","question":"Palm trees.","answer":"SAGOS"},{"num":"A33","question":"Joints, in carpentering.","answer":"MITERS"},{"num":"A34","question":"Thicket.","answer":"COPSE"},{"num":"A36","question":"Plus ___ (knickerbockers).","answer":"FOURS"},{"num":"A37","question":"Council.","answer":"SOVIET"},{"num":"A38","question":"Magna ___.","answer":"CARTA"},{"num":"A40","question":"Curved moldings.","answer":"OGEES"},{"num":"A41","question":"Dandy.","answer":"FOP"},{"num":"A42","question":"Old-time juvenile author.","answer":"ALGER"},{"num":"A46","question":"Whirring sound.","answer":"BIRR"},{"num":"A47","question":"Appear suddenly.","answer":"BOBUP"},{"num":"A49","question":"Passable.","answer":"SOSO"},{"num":"A50","question":"Epsilon's relative.","answer":"ETA"},{"num":"A51","question":"Strewn with stones, as a beach.","answer":"PEBBLED"},{"num":"A53","question":"World power.","answer":"USA"},{"num":"A54","question":"Meat dish.","answer":"RAGOUT"},{"num":"A56","question":"Families.","answer":"LINEAGES"},{"num":"A58","question":"Always: Poet.","answer":"ETERNE"},{"num":"A59","question":"Right of way, for example, in law.","answer":"EASEMENT"},{"num":"A60","question":"Close again.","answer":"RESEAL"},{"num":"A61","question":"Wipes out.","answer":"ERASES"}],"down":[{"num":"D1","question":"Melon.","answer":"CASABA"},{"num":"D2","question":"Slight movement.","answer":"RIPPLE"},{"num":"D3","question":"Click beetle.","answer":"ELATER"},{"num":"D4","question":"Thrice: Comb. form.","answer":"TER"},{"num":"D5","question":"Bulky boats.","answer":"ARKS"},{"num":"D6","question":"Tribesman on the move.","answer":"NOMAD"},{"num":"D7","question":"Members of the Black Watch.","answer":"SCOTS"},{"num":"D8","question":"Sinclair Lewis hero.","answer":"CASS"},{"num":"D9","question":"Burro.","answer":"ASS"},{"num":"D10","question":"Employer.","answer":"UTILIZER"},{"num":"D11","question":"Appreciative ones.","answer":"PRAISERS"},{"num":"D12","question":"\"Golden Treasury\" treasures.","answer":"SONNETS"},{"num":"D14","question":"Indian.","answer":"NAVAHO"},{"num":"D15","question":"Trapper's gear.","answer":"SNARES"},{"num":"D21","question":"Compass point.","answer":"NNW"},{"num":"D24","question":"More filmy.","answer":"WISPIER"},{"num":"D26","question":"Church books.","answer":"RITUALS"},{"num":"D28","question":"Facilitates.","answer":"EASES"},{"num":"D30","question":"Plant and animal life of a region.","answer":"BIOTA"},{"num":"D32","question":"Bring.","answer":"GET"},{"num":"D33","question":"Member of N. A. M.","answer":"MFR"},{"num":"D34","question":"Think over.","answer":"COGITATE"},{"num":"D35","question":"Surpluses.","answer":"OVERAGES"},{"num":"D37","question":"More subdued.","answer":"SOBERER"},{"num":"D38","question":"Paving stone.","answer":"COBBLE"},{"num":"D39","question":"Italian district.","answer":"APULIA"},{"num":"D41","question":"Watch pocket.","answer":"FOB"},{"num":"D43","question":"Chisels.","answer":"GOUGES"},{"num":"D44","question":"Member of ancient brotherhood.","answer":"ESSENE"},{"num":"D45","question":"Meat dishes.","answer":"ROASTS"},{"num":"D47","question":"East Indian pepper plant.","answer":"BETEL"},{"num":"D48","question":"Think: Fr.","answer":"PENSE"},{"num":"D51","question":"Arid plateau in the Andes.","answer":"PUNA"},{"num":"D52","question":"Game animal.","answer":"DEER"},{"num":"D55","question":"Pyrites.","answer":"ORE"},{"num":"D57","question":"Old church vessel.","answer":"AMA"}],"rawGrid":"\nCRETAN###SCAUPS\nAILERONS#CASTRO\nSPARKMAN#OSSIAN\nAPT#SAVANTS#LIN\nBLEW#DARNS#RISE\nAERIE#HEW#BIZET\n###SAGOS#MITERS\n#COPSE###FOURS#\nSOVIET#CARTA###\nOGEES#FOP#ALGER\nBIRR#BOBUP#SOSO\nETA#PEBBLED#USA\nRAGOUT#LINEAGES\nETERNE#EASEMENT\nRESEAL###ERASES\n","rawAcross":"\nA1. Native of Gnossus. ~ CRETAN\nA7. Sea ducks. ~ SCAUPS\nA13. Airplane parts. ~ AILERONS\nA16. Cuban notable. ~ CASTRO\nA17. Kefauver's running mate. ~ SPARKMAN\nA18. Bard of Irish folklore. ~ OSSIAN\nA19. Fitting. ~ APT\nA20. Learned men. ~ SAVANTS\nA22. Linden tree. ~ LIN\nA23. Was stormy. ~ BLEW\nA25. Mends. ~ DARNS\nA26. Begin. ~ RISE\nA27. Lofty abode. ~ AERIE\nA29. Chop. ~ HEW\nA30. French composer. ~ BIZET\nA31. Palm trees. ~ SAGOS\nA33. Joints, in carpentering. ~ MITERS\nA34. Thicket. ~ COPSE\nA36. Plus ___ (knickerbockers). ~ FOURS\nA37. Council. ~ SOVIET\nA38. Magna ___. ~ CARTA\nA40. Curved moldings. ~ OGEES\nA41. Dandy. ~ FOP\nA42. Old-time juvenile author. ~ ALGER\nA46. Whirring sound. ~ BIRR\nA47. Appear suddenly. ~ BOBUP\nA49. Passable. ~ SOSO\nA50. Epsilon's relative. ~ ETA\nA51. Strewn with stones, as a beach. ~ PEBBLED\nA53. World power. ~ USA\nA54. Meat dish. ~ RAGOUT\nA56. Families. ~ LINEAGES\nA58. Always: Poet. ~ ETERNE\nA59. Right of way, for example, in law. ~ EASEMENT\nA60. Close again. ~ RESEAL\nA61. Wipes out. ~ ERASES\n","rawDown":"\nD1. Melon. ~ CASABA\nD2. Slight movement. ~ RIPPLE\nD3. Click beetle. ~ ELATER\nD4. Thrice: Comb. form. ~ TER\nD5. Bulky boats. ~ ARKS\nD6. Tribesman on the move. ~ NOMAD\nD7. Members of the Black Watch. ~ SCOTS\nD8. Sinclair Lewis hero. ~ CASS\nD9. Burro. ~ ASS\nD10. Employer. ~ UTILIZER\nD11. Appreciative ones. ~ PRAISERS\nD12. \"Golden Treasury\" treasures. ~ SONNETS\nD14. Indian. ~ NAVAHO\nD15. Trapper's gear. ~ SNARES\nD21. Compass point. ~ NNW\nD24. More filmy. ~ WISPIER\nD26. Church books. ~ RITUALS\nD28. Facilitates. ~ EASES\nD30. Plant and animal life of a region. ~ BIOTA\nD32. Bring. ~ GET\nD33. Member of N. A. M. ~ MFR\nD34. Think over. ~ COGITATE\nD35. Surpluses. ~ OVERAGES\nD37. More subdued. ~ SOBERER\nD38. Paving stone. ~ COBBLE\nD39. Italian district. ~ APULIA\nD41. Watch pocket. ~ FOB\nD43. Chisels. ~ GOUGES\nD44. Member of ancient brotherhood. ~ ESSENE\nD45. Meat dishes. ~ ROASTS\nD47. East Indian pepper plant. ~ BETEL\nD48. Think: Fr. ~ PENSE\nD51. Arid plateau in the Andes. ~ PUNA\nD52. Game animal. ~ DEER\nD55. Pyrites. ~ ORE\nD57. Old church vessel. ~ AMA\n","rawMeta":"Title: New York Times, Wednesday, October 14, 1959\nAuthor: Unknown\nEditor: Margaret Farrar\nDate: 1959-10-14\n"}