{"meta":{"Title":"FORESTRY [New York Times, Sunday, February 1, 1959]","Author":"Harold T. Bers","Editor":"Margaret Farrar","Date":"1959-02-01"},"grid":[["S","C","O","T","S","#","O","A","R","S","#","I","S","M","S","#","M","E","W","E","D"],["A","L","L","E","E","#","T","R","U","E","#","A","P","I","A","#","A","L","O","N","E"],["C","E","D","A","R","C","H","E","S","T","#","M","R","S","Y","C","A","M","O","R","E"],["R","A","H","#","B","E","E","C","H","A","M","#","O","T","R","O","S","#","D","O","M"],["E","R","I","C","#","D","R","A","Y","#","A","M","U","L","E","T","#","G","E","L","S"],["#","#","C","A","P","E","S","#","#","P","R","A","T","E","#","E","A","R","N","#","#"],["T","O","K","L","A","S","#","D","A","I","R","Y","#","T","A","S","S","E","L","E","D"],["A","T","O","L","L","#","H","O","L","L","Y","W","O","O","D","#","P","E","E","V","E"],["C","E","R","A","M","#","O","R","D","E","#","O","B","E","A","M","#","N","G","O","N"],["K","A","Y","#","E","D","D","I","E","#","S","O","L","#","D","E","B","A","S","E","S"],["#","#","#","S","R","O","#","A","R","M","A","D","A","S","#","F","A","S","#","#","#"],["S","I","M","P","S","O","N","#","M","O","P","#","T","E","S","T","Y","#","T","E","D"],["H","O","A","R","#","M","A","T","E","S","#","B","E","N","E","#","T","R","A","D","E"],["A","L","P","I","D","#","P","I","N","E","H","U","R","S","T","#","R","A","N","G","Y"],["W","A","L","N","U","T","S","T","#","L","O","O","S","E","#","S","E","D","G","E","S"],["#","#","E","G","E","R","#","W","I","L","L","Y","#","#","S","T","E","A","L","#","#"],["Y","A","L","E","#","A","Z","I","N","E","S","#","A","S","I","A","#","R","E","S","T"],["U","R","E","#","S","M","E","L","T","#","T","A","T","T","E","R","S","#","W","H","O"],["C","R","A","B","A","P","P","L","E","S","#","C","H","A","R","T","E","R","O","A","K"],["C","A","F","E","S","#","P","O","R","E","#","H","O","E","R","#","L","E","O","R","A"],["A","S","S","E","S","#","O","W","N","S","#","E","L","L","A","#","F","A","D","D","Y"]],"across":[{"num":"A1","question":"Wallace's men.","answer":"SCOTS"},{"num":"A6","question":"Crewmen.","answer":"OARS"},{"num":"A10","question":"Offbeat systems.","answer":"ISMS"},{"num":"A14","question":"Shut up.","answer":"MEWED"},{"num":"A19","question":"Avenue, in Germany.","answer":"ALLEE"},{"num":"A20","question":"Authentic.","answer":"TRUE"},{"num":"A21","question":"Upolu port.","answer":"APIA"},{"num":"A22","question":"Unattached.","answer":"ALONE"},{"num":"A23","question":"Household storage space.","answer":"CEDARCHEST"},{"num":"A25","question":"Character in \"You Can't Take it With You.\"","answer":"MRSYCAMORE"},{"num":"A27","question":"Bowl sound.","answer":"RAH"},{"num":"A28","question":"Fiery English maestro.","answer":"BEECHAM"},{"num":"A30","question":"Others: Span.","answer":"OTROS"},{"num":"A31","question":"A DiMaggio.","answer":"DOM"},{"num":"A32","question":"Comedian Blore.","answer":"ERIC"},{"num":"A34","question":"Open cart.","answer":"DRAY"},{"num":"A35","question":"Charm.","answer":"AMULET"},{"num":"A37","question":"Crystallizes.","answer":"GELS"},{"num":"A38","question":"Invernesses.","answer":"CAPES"},{"num":"A40","question":"Jabber.","answer":"PRATE"},{"num":"A41","question":"Loch in Perthshire.","answer":"EARN"},{"num":"A43","question":"Gertrude Stein's alter ego.","answer":"TOKLAS"},{"num":"A45","question":"Wisconsin farm.","answer":"DAIRY"},{"num":"A47","question":"Having pendants.","answer":"TASSELED"},{"num":"A51","question":"Bikini, for one.","answer":"ATOLL"},{"num":"A52","question":"The movies.","answer":"HOLLYWOOD"},{"num":"A54","question":"Irritate: Colloq.","answer":"PEEVE"},{"num":"A55","question":"Molucca island.","answer":"CERAM"},{"num":"A56","question":"Gen. Wingate.","answer":"ORDE"},{"num":"A57","question":"Voodoo.","answer":"OBEAM"},{"num":"A59","question":"Figure of indeterminate sides.","answer":"NGON"},{"num":"A60","question":"Foster-brother of King Arthur.","answer":"KAY"},{"num":"A61","question":"Slugger Mathews.","answer":"EDDIE"},{"num":"A63","question":"Roman Helios.","answer":"SOL"},{"num":"A64","question":"Vitiates.","answer":"DEBASES"},{"num":"A66","question":"Rialto sign.","answer":"SRO"},{"num":"A67","question":"Fleets.","answer":"ARMADAS"},{"num":"A70","question":"Musical syllables.","answer":"FAS"},{"num":"A71","question":"Former name of a Duchess.","answer":"SIMPSON"},{"num":"A75","question":"Unruly tresses.","answer":"MOP"},{"num":"A76","question":"Irascible.","answer":"TESTY"},{"num":"A78","question":"Mr. Mack.","answer":"TED"},{"num":"A81","question":"Ancient.","answer":"HOAR"},{"num":"A82","question":"A pair.","answer":"MATES"},{"num":"A84","question":"Good: Ital.","answer":"BENE"},{"num":"A85","question":"Métier.","answer":"TRADE"},{"num":"A87","question":"Mountain range, in geology.","answer":"ALPID"},{"num":"A89","question":"Popular golf resort.","answer":"PINEHURST"},{"num":"A91","question":"Lank.","answer":"RANGY"},{"num":"A92","question":"Philadelphia thoroughfare sign.","answer":"WALNUTST"},{"num":"A94","question":"Detached.","answer":"LOOSE"},{"num":"A95","question":"Marsh plants.","answer":"SEDGES"},{"num":"A96","question":"\"Rome of Hungary.\"","answer":"EGER"},{"num":"A97","question":"Arthur Miller's salesman.","answer":"WILLY"},{"num":"A99","question":"Smuggle.","answer":"STEAL"},{"num":"A100","question":"Elmy campus.","answer":"YALE"},{"num":"A102","question":"Nitrogenous compounds.","answer":"AZINES"},{"num":"A104","question":"Ginkgo tree habitat.","answer":"ASIA"},{"num":"A106","question":"Siesta.","answer":"REST"},{"num":"A109","question":"Being: Suffix.","answer":"URE"},{"num":"A110","question":"Small fish.","answer":"SMELT"},{"num":"A111","question":"Shreds.","answer":"TATTERS"},{"num":"A114","question":"\"Sunny\" song.","answer":"WHO"},{"num":"A115","question":"The makings of jelly.","answer":"CRABAPPLES"},{"num":"A118","question":"Historic symbol of colonial days.","answer":"CHARTEROAK"},{"num":"A120","question":"Boulevard oases.","answer":"CAFES"},{"num":"A121","question":"Study (over).","answer":"PORE"},{"num":"A122","question":"Gardener.","answer":"HOER"},{"num":"A123","question":"Mrs. Arrowsmith.","answer":"LEORA"},{"num":"A124","question":"Nincompoops.","answer":"ASSES"},{"num":"A125","question":"Admits.","answer":"OWNS"},{"num":"A126","question":"She: Span.","answer":"ELLA"},{"num":"A127","question":"Addicted to crazes.","answer":"FADDY"}],"down":[{"num":"D1","question":"___ Coeur.","answer":"SACRE"},{"num":"D2","question":"Deforest.","answer":"CLEAR"},{"num":"D3","question":"Andrew Jackson.","answer":"OLDHICKORY"},{"num":"D4","question":"Darjeeling.","answer":"TEA"},{"num":"D5","question":"Native of Nis.","answer":"SERB"},{"num":"D6","question":"The rest.","answer":"OTHERS"},{"num":"D7","question":"Source of betel nuts.","answer":"ARECA"},{"num":"D8","question":"Abounding in cattails.","answer":"RUSHY"},{"num":"D9","question":"Silk: Ital.","answer":"SETA"},{"num":"D10","question":"\"I think, therefore ___.\"","answer":"IAM"},{"num":"D11","question":"Have buds.","answer":"SPROUT"},{"num":"D12","question":"Symbol from Druid days.","answer":"MISTLETOE"},{"num":"D13","question":"Author Joel ___.","answer":"SAYRE"},{"num":"D14","question":"Dutch river.","answer":"MAAS"},{"num":"D15","question":"New England trade-mark.","answer":"ELM"},{"num":"D16","question":"Piratic appendages.","answer":"WOODENLEGS"},{"num":"D17","question":"Sign up.","answer":"ENROL"},{"num":"D18","question":"A Taylor.","answer":"DEEMS"},{"num":"D24","question":"Transfers: Law.","answer":"CEDES"},{"num":"D26","question":"Shelters.","answer":"COTES"},{"num":"D29","question":"Shakespearean \"indeed!\"","answer":"MARRY"},{"num":"D33","question":"Lily.","answer":"CALLA"},{"num":"D36","question":"L. A. suburb.","answer":"MAYWOOD"},{"num":"D37","question":"___ grass.","answer":"GREENAS"},{"num":"D39","question":"Pilgrims.","answer":"PALMERS"},{"num":"D40","question":"Good supply.","answer":"PILE"},{"num":"D42","question":"Poplar: Poet.","answer":"ASP"},{"num":"D43","question":"Nail.","answer":"TACK"},{"num":"D44","question":"Great Barrier Island, N. Z.","answer":"OTEA"},{"num":"D45","question":"Genoese admiral.","answer":"DORIA"},{"num":"D46","question":"City functionaries.","answer":"ALDERMEN"},{"num":"D48","question":"Storm god of Babylonia.","answer":"ADAD"},{"num":"D49","question":"Bacchic cry.","answer":"EVOE"},{"num":"D50","question":"Scout groups.","answer":"DENS"},{"num":"D52","question":"Mason's trough.","answer":"HOD"},{"num":"D53","question":"Makers of religious offerings.","answer":"OBLATERS"},{"num":"D58","question":"Weight: Colloq.","answer":"MEFT"},{"num":"D62","question":"Judgment.","answer":"DOOM"},{"num":"D63","question":"Tree's life blood.","answer":"SAP"},{"num":"D65","question":"Laurel.","answer":"BAYTREE"},{"num":"D66","question":"Trap.","answer":"SPRINGE"},{"num":"D68","question":"Metz' river.","answer":"MOSELLE"},{"num":"D69","question":"Logic","answer":"SENSE"},{"num":"D71","question":"Noted Fabian.","answer":"SHAW"},{"num":"D72","question":"Kansas town.","answer":"IOLA"},{"num":"D73","question":"Toronto in the NHL.","answer":"MAPLELEAFS"},{"num":"D74","question":"Fabric surfaces.","answer":"NAPS"},{"num":"D77","question":"Bridge term.","answer":"SET"},{"num":"D78","question":"Summer mecca for music.","answer":"TANGLEWOOD"},{"num":"D79","question":"Slight lead.","answer":"EDGE"},{"num":"D80","question":"Algerian governors.","answer":"DEYS"},{"num":"D83","question":"G & S refrain.","answer":"TITWILLOW"},{"num":"D84","question":"Anchored float.","answer":"BUOY"},{"num":"D86","question":"Invention of the 1930's.","answer":"RADAR"},{"num":"D88","question":"Expected.","answer":"DUE"},{"num":"D90","question":"English composer.","answer":"HOLST"},{"num":"D93","question":"Type of steamer.","answer":"TRAMP"},{"num":"D95","question":"Genesis.","answer":"START"},{"num":"D98","question":"Hold in port.","answer":"INTERN"},{"num":"D99","question":"Craggy ridge.","answer":"SIERRA"},{"num":"D100","question":"The Joshua tree is one.","answer":"YUCCA"},{"num":"D101","question":"Robespierre's home town.","answer":"ARRAS"},{"num":"D103","question":"Fourth Marx brother.","answer":"ZEPPO"},{"num":"D104","question":"City in Mass.","answer":"ATHOL"},{"num":"D105","question":"Mme. de ___.","answer":"STAEL"},{"num":"D107","question":"Sliver of pottery.","answer":"SHARD"},{"num":"D108","question":"Wine.","answer":"TOKAY"},{"num":"D110","question":"Be impudent.","answer":"SASS"},{"num":"D112","question":"Symptom.","answer":"ACHE"},{"num":"D113","question":"Individual.","answer":"SELF"},{"num":"D116","question":"Leaf cutter or mason.","answer":"BEE"},{"num":"D117","question":"French possessive.","answer":"SES"},{"num":"D119","question":"Contemporary cartoonist.","answer":"REA"}],"rawGrid":"\nSCOTS#OARS#ISMS#MEWED\nALLEE#TRUE#APIA#ALONE\nCEDARCHEST#MRSYCAMORE\nRAH#BEECHAM#OTROS#DOM\nERIC#DRAY#AMULET#GELS\n##CAPES##PRATE#EARN##\nTOKLAS#DAIRY#TASSELED\nATOLL#HOLLYWOOD#PEEVE\nCERAM#ORDE#OBEAM#NGON\nKAY#EDDIE#SOL#DEBASES\n###SRO#ARMADAS#FAS###\nSIMPSON#MOP#TESTY#TED\nHOAR#MATES#BENE#TRADE\nALPID#PINEHURST#RANGY\nWALNUTST#LOOSE#SEDGES\n##EGER#WILLY##STEAL##\nYALE#AZINES#ASIA#REST\nURE#SMELT#TATTERS#WHO\nCRABAPPLES#CHARTEROAK\nCAFES#PORE#HOER#LEORA\nASSES#OWNS#ELLA#FADDY\n","rawAcross":"\nA1. Wallace's men. ~ SCOTS\nA6. Crewmen. ~ OARS\nA10. Offbeat systems. ~ ISMS\nA14. Shut up. ~ MEWED\nA19. Avenue, in Germany. ~ ALLEE\nA20. Authentic. ~ TRUE\nA21. Upolu port. ~ APIA\nA22. Unattached. ~ ALONE\nA23. Household storage space. ~ CEDARCHEST\nA25. Character in \"You Can't Take it With You.\" ~ MRSYCAMORE\nA27. Bowl sound. ~ RAH\nA28. Fiery English maestro. ~ BEECHAM\nA30. Others: Span. ~ OTROS\nA31. A DiMaggio. ~ DOM\nA32. Comedian Blore. ~ ERIC\nA34. Open cart. ~ DRAY\nA35. Charm. ~ AMULET\nA37. Crystallizes. ~ GELS\nA38. Invernesses. ~ CAPES\nA40. Jabber. ~ PRATE\nA41. Loch in Perthshire. ~ EARN\nA43. Gertrude Stein's alter ego. ~ TOKLAS\nA45. Wisconsin farm. ~ DAIRY\nA47. Having pendants. ~ TASSELED\nA51. Bikini, for one. ~ ATOLL\nA52. The movies. ~ HOLLYWOOD\nA54. Irritate: Colloq. ~ PEEVE\nA55. Molucca island. ~ CERAM\nA56. Gen. Wingate. ~ ORDE\nA57. Voodoo. ~ OBEAM\nA59. Figure of indeterminate sides. ~ NGON\nA60. Foster-brother of King Arthur. ~ KAY\nA61. Slugger Mathews. ~ EDDIE\nA63. Roman Helios. ~ SOL\nA64. Vitiates. ~ DEBASES\nA66. Rialto sign. ~ SRO\nA67. Fleets. ~ ARMADAS\nA70. Musical syllables. ~ FAS\nA71. Former name of a Duchess. ~ SIMPSON\nA75. Unruly tresses. ~ MOP\nA76. Irascible. ~ TESTY\nA78. Mr. Mack. ~ TED\nA81. Ancient. ~ HOAR\nA82. A pair. ~ MATES\nA84. Good: Ital. ~ BENE\nA85. Métier. ~ TRADE\nA87. Mountain range, in geology. ~ ALPID\nA89. Popular golf resort. ~ PINEHURST\nA91. Lank. ~ RANGY\nA92. Philadelphia thoroughfare sign. ~ WALNUTST\nA94. Detached. ~ LOOSE\nA95. Marsh plants. ~ SEDGES\nA96. \"Rome of Hungary.\" ~ EGER\nA97. Arthur Miller's salesman. ~ WILLY\nA99. Smuggle. ~ STEAL\nA100. Elmy campus. ~ YALE\nA102. Nitrogenous compounds. ~ AZINES\nA104. Ginkgo tree habitat. ~ ASIA\nA106. Siesta. ~ REST\nA109. Being: Suffix. ~ URE\nA110. Small fish. ~ SMELT\nA111. Shreds. ~ TATTERS\nA114. \"Sunny\" song. ~ WHO\nA115. The makings of jelly. ~ CRABAPPLES\nA118. Historic symbol of colonial days. ~ CHARTEROAK\nA120. Boulevard oases. ~ CAFES\nA121. Study (over). ~ PORE\nA122. Gardener. ~ HOER\nA123. Mrs. Arrowsmith. ~ LEORA\nA124. Nincompoops. ~ ASSES\nA125. Admits. ~ OWNS\nA126. She: Span. ~ ELLA\nA127. Addicted to crazes. ~ FADDY\n","rawDown":"\nD1. ___ Coeur. ~ SACRE\nD2. Deforest. ~ CLEAR\nD3. Andrew Jackson. ~ OLDHICKORY\nD4. Darjeeling. ~ TEA\nD5. Native of Nis. ~ SERB\nD6. The rest. ~ OTHERS\nD7. Source of betel nuts. ~ ARECA\nD8. Abounding in cattails. ~ RUSHY\nD9. Silk: Ital. ~ SETA\nD10. \"I think, therefore ___.\" ~ IAM\nD11. Have buds. ~ SPROUT\nD12. Symbol from Druid days. ~ MISTLETOE\nD13. Author Joel ___. ~ SAYRE\nD14. Dutch river. ~ MAAS\nD15. New England trade-mark. ~ ELM\nD16. Piratic appendages. ~ WOODENLEGS\nD17. Sign up. ~ ENROL\nD18. A Taylor. ~ DEEMS\nD24. Transfers: Law. ~ CEDES\nD26. Shelters. ~ COTES\nD29. Shakespearean \"indeed!\" ~ MARRY\nD33. Lily. ~ CALLA\nD36. L. A. suburb. ~ MAYWOOD\nD37. ___ grass. ~ GREENAS\nD39. Pilgrims. ~ PALMERS\nD40. Good supply. ~ PILE\nD42. Poplar: Poet. ~ ASP\nD43. Nail. ~ TACK\nD44. Great Barrier Island, N. Z. ~ OTEA\nD45. Genoese admiral. ~ DORIA\nD46. City functionaries. ~ ALDERMEN\nD48. Storm god of Babylonia. ~ ADAD\nD49. Bacchic cry. ~ EVOE\nD50. Scout groups. ~ DENS\nD52. Mason's trough. ~ HOD\nD53. Makers of religious offerings. ~ OBLATERS\nD58. Weight: Colloq. ~ MEFT\nD62. Judgment. ~ DOOM\nD63. Tree's life blood. ~ SAP\nD65. Laurel. ~ BAYTREE\nD66. Trap. ~ SPRINGE\nD68. Metz' river. ~ MOSELLE\nD69. Logic ~ SENSE\nD71. Noted Fabian. ~ SHAW\nD72. Kansas town. ~ IOLA\nD73. Toronto in the NHL. ~ MAPLELEAFS\nD74. Fabric surfaces. ~ NAPS\nD77. Bridge term. ~ SET\nD78. Summer mecca for music. ~ TANGLEWOOD\nD79. Slight lead. ~ EDGE\nD80. Algerian governors. ~ DEYS\nD83. G & S refrain. ~ TITWILLOW\nD84. Anchored float. ~ BUOY\nD86. Invention of the 1930's. ~ RADAR\nD88. Expected. ~ DUE\nD90. English composer. ~ HOLST\nD93. Type of steamer. ~ TRAMP\nD95. Genesis. ~ START\nD98. Hold in port. ~ INTERN\nD99. Craggy ridge. ~ SIERRA\nD100. The Joshua tree is one. ~ YUCCA\nD101. Robespierre's home town. ~ ARRAS\nD103. Fourth Marx brother. ~ ZEPPO\nD104. City in Mass. ~ ATHOL\nD105. Mme. de ___. ~ STAEL\nD107. Sliver of pottery. ~ SHARD\nD108. Wine. ~ TOKAY\nD110. Be impudent. ~ SASS\nD112. Symptom. ~ ACHE\nD113. Individual. ~ SELF\nD116. Leaf cutter or mason. ~ BEE\nD117. French possessive. ~ SES\nD119. Contemporary cartoonist. ~ REA\n","rawMeta":"Title: FORESTRY [New York Times, Sunday, February 1, 1959]\nAuthor: Harold T. Bers\nEditor: Margaret Farrar\nDate: 1959-02-01\n"}